README.md
setup.py
pywarface/__init__.py
pywarface/achievement.py
pywarface/region.py
pywarface/server.py
pywarface/server_test.py
pywarface/user.py
pywarface/userclass.py
pywarface.egg-info/PKG-INFO
pywarface.egg-info/SOURCES.txt
pywarface.egg-info/dependency_links.txt
pywarface.egg-info/requires.txt
pywarface.egg-info/top_level.txt