Metadata-Version: 1.0
Name: pywarface
Version: 1.0
Summary: A Python library for interacting with the my.com Warface API
Home-page: https://retrylife.ca/
Author: Evan Pratten
Author-email: ewpratten@retrylife.ca
License: GPLv3
Platform: UNKNOWN
